tests/unit/__init__.py
tests/unit/test_data_structure_utils.py
tests/unit/test_file_helper.py
tests/unit/test_spec.py
tests/unit/test_string_utils.py
tests/unit/test_temp_files_helper.py
tests/unit/test_time_utils.py
training_noodles/__init__.py
training_noodles/arguments.py
training_noodles/cli.py
training_noodles/commands_runner.py
training_noodles/data_structure_utils.py
training_noodles/file_helper.py
training_noodles/logger.py
training_noodles/logging_utils.py
training_noodles/noodles.py
training_noodles/runner.py
training_noodles/spec.py
training_noodles/string_utils.py
training_noodles/temp_files_helper.py
training_noodles/time_utils.py
training_noodles/specs/defaults.yml
training_noodles-1.2.2.dist-info/LICENSE.txt
training_noodles-1.2.2.dist-info/METADATA
training_noodles-1.2.2.dist-info/WHEEL
training_noodles-1.2.2.dist-info/entry_points.txt
training_noodles-1.2.2.dist-info/top_level.txt
training_noodles-1.2.2.dist-info/RECORD
