Metadata-Version: 2.1
Name: training-noodles
Version: 1.2.2
Summary: Train multiple programs on multiple servers without pain
Home-page: https://github.com/elsa-lab/training-noodles
Author: Shawn Chang
Author-email: shawn420@gapp.nthu.edu.tw
License: UNKNOWN
Project-URL: Bug Reports, https://github.com/elsa-lab/training-noodles/issues
Project-URL: Source, https://github.com/elsa-lab/training-noodles
Keywords: training deployment tools noodles ssh
Platform: UNKNOWN
Classifier: Development Status :: 3 - Alpha
Classifier: Intended Audience :: Developers
Classifier: Topic :: Scientific/Engineering :: Artificial Intelligence
Classifier: Topic :: System :: Distributed Computing
Classifier: Topic :: System :: Installation/Setup
Classifier: Topic :: System :: Monitoring
Classifier: Topic :: Utilities
Classifier: License :: OSI Approved :: MIT License
Classifier: Programming Language :: Python :: 3
Classifier: Programming Language :: Python :: 3.5
Classifier: Programming Language :: Python :: 3.6
Classifier: Programming Language :: Python :: 3.7
Requires-Python: >=3.5, <4
Requires-Dist: oyaml (==0.9)
Provides-Extra: dev
Requires-Dist: check-manifest ; extra == 'dev'
Provides-Extra: test
Requires-Dist: coverage ; extra == 'test'
